pympistandard/__init__.py
pympistandard/_kinds.py
pympistandard/callback.py
pympistandard/data/__init__.py
pympistandard/data/apis.json
pympistandard/export.py
pympistandard/expressions.py
pympistandard/f08.py
pympistandard/f90.py
pympistandard/isoc.py
pympistandard/kind.py
pympistandard/lis.py
pympistandard/namespace.py
pympistandard/parameter.py
pympistandard/predefined_function.py
pympistandard/procedure.py
pympistandard/storage.py
pympistandard/symbol.py
pympistandard/version.py
pympistandard-0.1.1.dist-info/LICENSE
pympistandard-0.1.1.dist-info/WHEEL
pympistandard-0.1.1.dist-info/METADATA
pympistandard-0.1.1.dist-info/RECORD
